{
  "project_info": {
    "project_number": "251674313106",
    "firebase_url": "https://zatsepicoffee-a8b39-default-rtdb.firebaseio.com",
    "project_id": "zatsepicoffee-a8b39",
    "storage_bucket": "zatsepicoffee-a8b39.appspot.com"
  },
  "client": [
    {
      "client_info": {
        "mobilesdk_app_id": "1:251674313106:android:d0e64e3acd7b64b93f814b",
        "android_client_info": {
          "package_name": "com.example.zatsepicoffee_v1"
        }
      },
      "oauth_client": [
        {
          "client_id": "251674313106-6hiblq8dma0binb2nu99j5l63e4sdt0e.apps.googleusercontent.com",
          "client_type": 1,
          "android_info": {
            "package_name": "com.example.zatsepicoffee_v1",
            "certificate_hash": "796f9770a0dba80576d13628124e444d76980175"
          }
        },
        {
          "client_id": "251674313106-j7jp863ph9oke1j7bpv213d4f1jt2frk.apps.googleusercontent.com",
          "client_type": 3
        }
      ],
      "api_key": [
        {
          "current_key": "AIzaSyBplD6pgiMQ32-sEBm5a7yFyPdri79qAcw"
        }
      ],
      "services": {
        "appinvite_service": {
          "other_platform_oauth_client": [
            {
              "client_id": "251674313106-j7jp863ph9oke1j7bpv213d4f1jt2frk.apps.googleusercontent.com",
              "client_type": 3
            }
          ]
        }
      }
    }
  ],
  "configuration_version": "1"
}
